MCintegration/__init__.py
MCintegration/base.py
MCintegration/base_test.py
MCintegration/integrators.py
MCintegration/integrators_test.py
MCintegration/maps.py
MCintegration/maps_test.py
MCintegration/mc_multicpu_test.py
MCintegration/utils.py
MCintegration/utils_test.py
mcintegration-1.0.0.dist-info/LICENSE
mcintegration-1.0.0.dist-info/METADATA
mcintegration-1.0.0.dist-info/WHEEL
mcintegration-1.0.0.dist-info/top_level.txt
mcintegration-1.0.0.dist-info/RECORD
